CHANGELOG.rst
LICENSE_GPL2.0.txt
LICENSE_LGPL_2.1.txt
MANIFEST.in
README.rst
setup.py
src/rebus/__init__.py
src/rebus/defaults.py
src/rebus/exceptions.py
src/rebus/tests.py
src/rebus.egg-info/PKG-INFO
src/rebus.egg-info/SOURCES.txt
src/rebus.egg-info/dependency_links.txt
src/rebus.egg-info/requires.txt
src/rebus.egg-info/top_level.txt