Metadata-Version: 1.1
Name: rebus
Version: 0.2
Summary: rebus - Generate base64-encoded strings consisting of alphanumeric symbols only.
Home-page: https://github.com/barseghyanartur/rebus/
Author: Artur Barseghyan
Author-email: artur.barseghyan@gmail.com
License: GPL 2.0/LGPL 2.1
Keywords: b32encode,b64encode,b32decode,b64decode
Platform: UNKNOWN
Classifier: Programming Language :: Python :: 2.6
Classifier: Programming Language :: Python :: 2.7
Classifier: Programming Language :: Python :: 3
Classifier: Programming Language :: Python :: 3.3
Classifier: Environment :: Web Environment
Classifier: License :: OSI Approved :: GNU General Public License v2 (GPLv2)
Classifier: License :: OSI Approved :: GNU Lesser General Public License v2 or later (LGPLv2+)
Classifier: Framework :: Django
Classifier: Intended Audience :: Developers
Classifier: Operating System :: OS Independent
Classifier: Topic :: Text Processing
Classifier: Development Status :: 4 - Beta
